LICENSE
MANIFEST.in
README.rst
requirements.txt
setup.py
extras/bash_completion.sh
gonzo/__init__.py
gonzo/config.py
gonzo/exceptions.py
gonzo/utils.py
gonzo.egg-info/PKG-INFO
gonzo.egg-info/SOURCES.txt
gonzo.egg-info/dependency_links.txt
gonzo.egg-info/entry_points.txt
gonzo.egg-info/not-zip-safe
gonzo.egg-info/requires.txt
gonzo.egg-info/top_level.txt
gonzo/clouds/__init__.py
gonzo/clouds/compute.py
gonzo/clouds/dns.py
gonzo/contrib/__init__.py
gonzo/contrib/checks.py
gonzo/helpers/__init__.py
gonzo/helpers/document_loader.py
gonzo/helpers/git.py
gonzo/scripts/__init__.py
gonzo/scripts/base.py
gonzo/scripts/config.py
gonzo/scripts/launch.py
gonzo/scripts/list_.py
gonzo/scripts/terminate.py
gonzo/scripts/utils.py
gonzo/scripts/image/__init__.py
gonzo/scripts/image/create.py
gonzo/scripts/image/delete.py
gonzo/tasks/__init__.py
gonzo/tasks/apache.py
gonzo/tasks/celery.py
gonzo/tasks/gonzo.py
gonzo/tasks/pip.py
gonzo/tasks/puppet.py
gonzo/tasks/release.py
gonzo/tasks/supervisord.py
gonzo/test_utils/__init__.py