Metadata-Version: 1.1
Name: gonzo
Version: 0.4.2
Summary: Instance and release management made easy
Home-page: https://github.com/onefinestay/gonzo
Author: onefinestay
Author-email: engineering@onefinestay.com
License: UNKNOWN
Platform: UNKNOWN
Classifier: Development Status :: 3 - Alpha
Classifier: Programming Language :: Python
Classifier: Intended Audience :: Developers
Classifier: Natural Language :: English
Classifier: Topic :: Software Development
Classifier: Topic :: Utilities
Classifier: Environment :: Console
